{
  "project_info": {
    "project_number": "623260000704",
    "project_id": "strafio-admin",
    "storage_bucket": "strafio-admin.appspot.com"
  },
  "client": [
    {
      "client_info": {
        "mobilesdk_app_id": "1:623260000704:android:ae92c0ea0bdb20a10f6825",
        "android_client_info": {
          "package_name": "com.lp.strafio.strafio"
        }
      },
      "oauth_client": [
        {
          "client_id": "623260000704-f0hkqi9bu8c04m7od6v5t2f54o4thgqi.apps.googleusercontent.com",
          "client_type": 3
        }
      ],
      "api_key": [
        {
          "current_key": "AIzaSyBk0OpNwRYE9lfCWnPLEs7l1_VbYl06Zfg"
        }
      ],
      "services": {
        "appinvite_service": {
          "other_platform_oauth_client": [
            {
              "client_id": "623260000704-f0hkqi9bu8c04m7od6v5t2f54o4thgqi.apps.googleusercontent.com",
              "client_type": 3
            }
          ]
        }
      }
    }
  ],
  "configuration_version": "1"
}